pg_xmlsig-0.0.3.dist-info/DESCRIPTION.rst
pg_xmlsig-0.0.3.dist-info/METADATA
pg_xmlsig-0.0.3.dist-info/RECORD
pg_xmlsig-0.0.3.dist-info/WHEEL
pg_xmlsig-0.0.3.dist-info/metadata.json
pg_xmlsig-0.0.3.dist-info/top_level.txt
pgxmlsig/__init__.py
pgxmlsig/constants.py
pgxmlsig/ns.py
pgxmlsig/signature_context.py
pgxmlsig/template.py
pgxmlsig/utils.py
pgxmlsig/algorithms/__init__.py
pgxmlsig/algorithms/base.py
pgxmlsig/algorithms/hmac.py
pgxmlsig/algorithms/rsa.py
pgxmlsig/data/xmldsig-core-schema.xsd
